groupedpaneldatamodels/.DS_Store
groupedpaneldatamodels/__init__.py
groupedpaneldatamodels/information_criteria.py
groupedpaneldatamodels/model.py
groupedpaneldatamodels/results.py
groupedpaneldatamodels/test.ipynb
groupedpaneldatamodels/utility.py
groupedpaneldatamodels/models/__init__.py
groupedpaneldatamodels/models/ando_bai.py
groupedpaneldatamodels/models/bonhomme_manresa.py
groupedpaneldatamodels/models/su_ju.py
groupedpaneldatamodels/models/su_shi_phillips.py
groupedpaneldatamodels/utils/__init__.py
groupedpaneldatamodels/utils/lstsq.py
groupedpaneldatamodels-0.1.2.dist-info/licenses/LICENSE
groupedpaneldatamodels-0.1.2.dist-info/WHEEL
groupedpaneldatamodels-0.1.2.dist-info/METADATA
groupedpaneldatamodels-0.1.2.dist-info/RECORD
